Metadata-Version: 2.1
Name: GetPcInfo
Version: 2.0
Summary: GetPcInfo
Home-page: https://No.com
Author: pythonking
Author-email: youremail@none.com
License: UNKNOWN
Platform: UNKNOWN
